tinypubsub/__init__.py
tinypubsub/publisher.py
tinypubsub/py.typed
tinypubsub/simple/__init__.py
tinypubsub/simple/publisher.py
tinypubsub/subscription.py
tinypubsub/weakref/__init__.py
tinypubsub/weakref/publisher.py
tinypubsub-0.1.0.dist-info/LICENSE
tinypubsub-0.1.0.dist-info/WHEEL
tinypubsub-0.1.0.dist-info/METADATA
tinypubsub-0.1.0.dist-info/RECORD
