Metadata-Version: 2.1
Name: tinypubsub
Version: 0.1.0
Summary: Tiny pub-sub (observer) pattern implementation
Home-page: https://github.com/nekonoshiri/tinypubsub
License: MIT
Keywords: pubsub,observer
Author: Shiri Nekono
Author-email: gexira.halen.toms@gmail.com
Maintainer: Shiri Nekono
Maintainer-email: gexira.halen.toms@gmail.com
Requires-Python: >=3.7,<4.0
Classifier: Development Status :: 4 - Beta
Classifier: Intended Audience :: Developers
Classifier: License :: OSI Approved :: MIT License
Classifier: Programming Language :: Python :: 3
Classifier: Programming Language :: Python :: 3.7
Classifier: Programming Language :: Python :: 3.8
Classifier: Programming Language :: Python :: 3.9
Classifier: Topic :: Software Development :: Libraries
Classifier: Topic :: Utilities
Project-URL: Documentation, https://github.com/nekonoshiri/tinypubsub
Project-URL: Repository, https://github.com/nekonoshiri/tinypubsub
